mt5_grpc_proto/__init__.py
mt5_grpc_proto/account_pb2.py
mt5_grpc_proto/account_pb2_grpc.py
mt5_grpc_proto/common_pb2.py
mt5_grpc_proto/common_pb2_grpc.py
mt5_grpc_proto/deal_pb2.py
mt5_grpc_proto/deal_pb2_grpc.py
mt5_grpc_proto/history_orders_pb2.py
mt5_grpc_proto/history_orders_pb2_grpc.py
mt5_grpc_proto/initialize_pb2.py
mt5_grpc_proto/initialize_pb2_grpc.py
mt5_grpc_proto/market_book_pb2.py
mt5_grpc_proto/market_book_pb2_grpc.py
mt5_grpc_proto/market_data_pb2.py
mt5_grpc_proto/market_data_pb2_grpc.py
mt5_grpc_proto/order_calc_pb2.py
mt5_grpc_proto/order_calc_pb2_grpc.py
mt5_grpc_proto/order_check_pb2.py
mt5_grpc_proto/order_check_pb2_grpc.py
mt5_grpc_proto/order_pb2.py
mt5_grpc_proto/order_pb2_grpc.py
mt5_grpc_proto/position_pb2.py
mt5_grpc_proto/position_pb2_grpc.py
mt5_grpc_proto/symbol_info_pb2.py
mt5_grpc_proto/symbol_info_pb2_grpc.py
mt5_grpc_proto/symbol_info_tick_pb2.py
mt5_grpc_proto/symbol_info_tick_pb2_grpc.py
mt5_grpc_proto/symbols_pb2.py
mt5_grpc_proto/symbols_pb2_grpc.py
mt5_grpc_proto/terminal_pb2.py
mt5_grpc_proto/terminal_pb2_grpc.py
mt5_grpc_proto/trade_pb2.py
mt5_grpc_proto/trade_pb2_grpc.py
mt5_grpc_proto-0.2.1.dist-info/METADATA
mt5_grpc_proto-0.2.1.dist-info/WHEEL
mt5_grpc_proto-0.2.1.dist-info/top_level.txt
mt5_grpc_proto-0.2.1.dist-info/RECORD
